odoo10_addon_base_zugferd-10.0.1.0.0.99.dev14-nspkg.pth
odoo/addons/base_zugferd/README.rst
odoo/addons/base_zugferd/__init__.py
odoo/addons/base_zugferd/__manifest__.py
odoo/addons/base_zugferd/data/zugferd_codes.xml
odoo/addons/base_zugferd/data/xsd-factur-x/FACTUR-X_BASIC-WL.xsd
odoo/addons/base_zugferd/data/xsd-factur-x/FACTUR-X_BASIC-WL_urn_un_unece_uncefact_data_standard_QualifiedDataType_100.xsd
odoo/addons/base_zugferd/data/xsd-factur-x/FACTUR-X_BASIC-WL_urn_un_unece_uncefact_data_standard_ReusableAggregateBusinessInformationEntity_100.xsd
odoo/addons/base_zugferd/data/xsd-factur-x/FACTUR-X_BASIC-WL_urn_un_unece_uncefact_data_standard_UnqualifiedDataType_100.xsd
odoo/addons/base_zugferd/data/xsd-factur-x/FACTUR-X_EN16931.xsd
odoo/addons/base_zugferd/data/xsd-factur-x/FACTUR-X_EN16931_urn_un_unece_uncefact_data_standard_QualifiedDataType_100.xsd
odoo/addons/base_zugferd/data/xsd-factur-x/FACTUR-X_EN16931_urn_un_unece_uncefact_data_standard_ReusableAggregateBusinessInformationEntity_100.xsd
odoo/addons/base_zugferd/data/xsd-factur-x/FACTUR-X_EN16931_urn_un_unece_uncefact_data_standard_UnqualifiedDataType_100.xsd
odoo/addons/base_zugferd/data/xsd-factur-x/FACTUR-X_EXTENDED.xsd
odoo/addons/base_zugferd/data/xsd-factur-x/FACTUR-X_EXTENDED_urn_un_unece_uncefact_data_standard_QualifiedDataType_100.xsd
odoo/addons/base_zugferd/data/xsd-factur-x/FACTUR-X_EXTENDED_urn_un_unece_uncefact_data_standard_ReusableAggregateBusinessInformationEntity_100.xsd
odoo/addons/base_zugferd/data/xsd-factur-x/FACTUR-X_EXTENDED_urn_un_unece_uncefact_data_standard_UnqualifiedDataType_100.xsd
odoo/addons/base_zugferd/data/xsd-factur-x/Factur-X_extension_schema.xmp
odoo/addons/base_zugferd/data/xsd-zugferd/ZUGFeRD1p0.xsd
odoo/addons/base_zugferd/data/xsd-zugferd/ZUGFeRD1p0_urn_un_unece_uncefact_data_standard_QualifiedDataType_12.xsd
odoo/addons/base_zugferd/data/xsd-zugferd/ZUGFeRD1p0_urn_un_unece_uncefact_data_standard_ReusableAggregateBusinessInformationEntity_12.xsd
odoo10_addon_base_zugferd-10.0.1.0.0.99.dev14.dist-info/METADATA
odoo10_addon_base_zugferd-10.0.1.0.0.99.dev14.dist-info/WHEEL
odoo10_addon_base_zugferd-10.0.1.0.0.99.dev14.dist-info/namespace_packages.txt
odoo10_addon_base_zugferd-10.0.1.0.0.99.dev14.dist-info/top_level.txt
odoo10_addon_base_zugferd-10.0.1.0.0.99.dev14.dist-info/RECORD
